{"base_name_url":"https:\/\/www.imdb.com\/name","participant_ids":"nm5232273~nm12017223~nm2175457~nm12017236~","title_id":"tt13357042","rating":"0.0","base_url":"https:\/\/www.imdb.com","description":"As a demon and a fallen angel battle for his soul, a tormented serial killer is stalked by the ghosts of his past victims and hunted by detectives searching for his latest prey.","runtime":"81 min","source":"imdb","title":"Devil's Prey","director_ids":"nm10650913~","title_url":"\/title\/tt13357042\/?ref_=adv_li_tt","director_names":"Lincoln Casimir~","genres":"Horror, Mystery, Thriller","base_title_url":"https:\/\/www.imdb.com\/title","participant_names":"Leeden Anderson~Emily Battles~Carol Bayruns~Zoe Belasco~"}